binhistory/__init__.py
binhistory/_binlog.py
binhistory/_binlogentry.py
binhistory/defaults.py
binhistory/exceptions.py
pybinhistory-0.7.0.dist-info/LICENSE
pybinhistory-0.7.0.dist-info/METADATA
pybinhistory-0.7.0.dist-info/WHEEL
pybinhistory-0.7.0.dist-info/top_level.txt
pybinhistory-0.7.0.dist-info/RECORD
